<?xml version="1.0" encoding="UTF-8"?>
<databaseChangeLog
        xmlns="http://www.liquibase.org/xml/ns/dbchangelog"
        xmlns:xsi="http://www.w3.org/2001/XMLSchema-instance"
        xsi:schemaLocation="http://www.liquibase.org/xml/ns/dbchangelog
                      http://www.liquibase.org/xml/ns/dbchangelog/dbchangelog-3.8.xsd">

    <property name="now" value="now()" dbms="postgresql"/>

    <changeSet id="007-ins_mdm30_status_transition_wf_doc" author="EAlbinets">
        <insert tableName="mdm30_status_transition" dbms="postgresql, mssql, hsqldb">
            <column name="ID" value="1169bec6-9960-11ec-b909-0242ac120002"/>
            <column name="START_STATUS" value="a00da87c-8f05-11ec-b909-0242ac120002"/>
            <column name="END_STATUS" value="160da87c-8f05-11ec-b909-0242ac120002"/>
            <column name="STATUS_MODEL_ID" value="84e9750a-92e6-11ec-b909-0242ac120002"/>
            <column name="DESCRIPTION" value="Черновик"/>
            <column name="START_DATE" value="2015-01-01"/>
            <column name="END_DATE" value="9999-12-31"/>
            <column name="CREATED_BY" value="suvv-admin"/>
            <column name="CREATED_DATE" valueDate="${now}"/>
            <column name="LAST_MODIFIED_DATE" valueDate="${now}"/>
            <column name="version" value="1"/>
        </insert>


        <insert tableName="mdm30_status_transition" dbms="postgresql, mssql, hsqldb">
            <column name="ID" value="1269bec6-9960-11ec-b909-0242ac120002"/>
            <column name="START_STATUS" value="a00da87c-8f05-11ec-b909-0242ac120002"/>
            <column name="END_STATUS" value="900da87c-8f05-11ec-b909-0242ac120002"/>
            <column name="STATUS_MODEL_ID" value="84e9750a-92e6-11ec-b909-0242ac120002"/>
            <column name="DESCRIPTION" value="Черновик"/>
            <column name="START_DATE" value="2015-01-01"/>
            <column name="END_DATE" value="9999-12-31"/>
            <column name="CREATED_BY" value="suvv-admin"/>
            <column name="CREATED_DATE" valueDate="${now}"/>
            <column name="LAST_MODIFIED_DATE" valueDate="${now}"/>
            <column name="version" value="1"/>
        </insert>


        <insert tableName="mdm30_status_transition" dbms="postgresql, mssql, hsqldb">
            <column name="ID" value="1369bec6-9960-11ec-b909-0242ac120002"/>
            <column name="START_STATUS" value="160da87c-8f05-11ec-b909-0242ac120002"/>
            <column name="END_STATUS" value="1e90a87c-8f05-11ec-b909-0242ac120002"/>
            <column name="STATUS_MODEL_ID" value="84e9750a-92e6-11ec-b909-0242ac120002"/>
            <column name="DESCRIPTION" value="Согласование Документа Технологом"/>
            <column name="START_DATE" value="2015-01-01"/>
            <column name="END_DATE" value="9999-12-31"/>
            <column name="CREATED_BY" value="suvv-admin"/>
            <column name="CREATED_DATE" valueDate="${now}"/>
            <column name="LAST_MODIFIED_DATE" valueDate="${now}"/>
            <column name="version" value="1"/>
        </insert>

        <insert tableName="mdm30_status_transition" dbms="postgresql, mssql, hsqldb">
            <column name="ID" value="1469bec6-9960-11ec-b909-0242ac120002"/>
            <column name="START_STATUS" value="160da87c-8f05-11ec-b909-0242ac120002"/>
            <column name="END_STATUS" value="100da87c-8f05-11ec-b909-0242ac120002"/>
            <column name="STATUS_MODEL_ID" value="84e9750a-92e6-11ec-b909-0242ac120002"/>
            <column name="DESCRIPTION" value="Согласование Документа Технологом"/>
            <column name="START_DATE" value="2015-01-01"/>
            <column name="END_DATE" value="9999-12-31"/>
            <column name="CREATED_BY" value="suvv-admin"/>
            <column name="CREATED_DATE" valueDate="${now}"/>
            <column name="LAST_MODIFIED_DATE" valueDate="${now}"/>
            <column name="version" value="1"/>
        </insert>

        <insert tableName="mdm30_status_transition" dbms="postgresql, mssql, hsqldb">
            <column name="ID" value="1569bec6-9960-11ec-b909-0242ac120002"/>
            <column name="START_STATUS" value="160da87c-8f05-11ec-b909-0242ac120002"/>
            <column name="END_STATUS" value="900da87c-8f05-11ec-b909-0242ac120002"/>
            <column name="STATUS_MODEL_ID" value="84e9750a-92e6-11ec-b909-0242ac120002"/>
            <column name="DESCRIPTION" value="Согласование Документа Технологом"/>
            <column name="START_DATE" value="2015-01-01"/>
            <column name="END_DATE" value="9999-12-31"/>
            <column name="CREATED_BY" value="suvv-admin"/>
            <column name="CREATED_DATE" valueDate="${now}"/>
            <column name="LAST_MODIFIED_DATE" valueDate="${now}"/>
            <column name="version" value="1"/>
        </insert>

        <insert tableName="mdm30_status_transition" dbms="postgresql, mssql, hsqldb">
            <column name="ID" value="1769bec6-9960-11ec-b909-0242ac120002"/>
            <column name="START_STATUS" value="1e90a87c-8f05-11ec-b909-0242ac120002"/>
            <column name="END_STATUS" value="1f90a87c-8f05-11ec-b909-0242ac120002"/>
            <column name="STATUS_MODEL_ID" value="84e9750a-92e6-11ec-b909-0242ac120002"/>
            <column name="DESCRIPTION" value="Обеспечение утверждения Документа Технологом"/>
            <column name="START_DATE" value="2015-01-01"/>
            <column name="END_DATE" value="9999-12-31"/>
            <column name="CREATED_BY" value="suvv-admin"/>
            <column name="CREATED_DATE" valueDate="${now}"/>
            <column name="LAST_MODIFIED_DATE" valueDate="${now}"/>
            <column name="version" value="1"/>
        </insert>

        <insert tableName="mdm30_status_transition" dbms="postgresql, mssql, hsqldb">
            <column name="ID" value="1869bec6-9960-11ec-b909-0242ac120002"/>
            <column name="START_STATUS" value="1e90a87c-8f05-11ec-b909-0242ac120002"/>
            <column name="END_STATUS" value="160da87c-8f05-11ec-b909-0242ac120002"/>
            <column name="STATUS_MODEL_ID" value="84e9750a-92e6-11ec-b909-0242ac120002"/>
            <column name="DESCRIPTION" value="Обеспечение утверждения Документа Технологом"/>
            <column name="START_DATE" value="2015-01-01"/>
            <column name="END_DATE" value="9999-12-31"/>
            <column name="CREATED_BY" value="suvv-admin"/>
            <column name="CREATED_DATE" valueDate="${now}"/>
            <column name="LAST_MODIFIED_DATE" valueDate="${now}"/>
            <column name="version" value="1"/>
        </insert>

        <insert tableName="mdm30_status_transition" dbms="postgresql, mssql, hsqldb">
            <column name="ID" value="1969bec6-9960-11ec-b909-0242ac120002"/>
            <column name="START_STATUS" value="1e90a87c-8f05-11ec-b909-0242ac120002"/>
            <column name="END_STATUS" value="900da87c-8f05-11ec-b909-0242ac120002"/>
            <column name="STATUS_MODEL_ID" value="84e9750a-92e6-11ec-b909-0242ac120002"/>
            <column name="DESCRIPTION" value="Обеспечение утверждения Документа Технологом"/>
            <column name="START_DATE" value="2015-01-01"/>
            <column name="END_DATE" value="9999-12-31"/>
            <column name="CREATED_BY" value="suvv-admin"/>
            <column name="CREATED_DATE" valueDate="${now}"/>
            <column name="LAST_MODIFIED_DATE" valueDate="${now}"/>
            <column name="version" value="1"/>
        </insert>

        <insert tableName="mdm30_status_transition" dbms="postgresql, mssql, hsqldb">
            <column name="ID" value="1A69bec6-9960-11ec-b909-0242ac120002"/>
            <column name="START_STATUS" value="100da87c-8f05-11ec-b909-0242ac120002"/>
            <column name="END_STATUS" value="160da87c-8f05-11ec-b909-0242ac120002"/>
            <column name="STATUS_MODEL_ID" value="84e9750a-92e6-11ec-b909-0242ac120002"/>
            <column name="DESCRIPTION" value="Корректировка Документа"/>
            <column name="START_DATE" value="2015-01-01"/>
            <column name="END_DATE" value="9999-12-31"/>
            <column name="CREATED_BY" value="suvv-admin"/>
            <column name="CREATED_DATE" valueDate="${now}"/>
            <column name="LAST_MODIFIED_DATE" valueDate="${now}"/>
            <column name="version" value="1"/>
        </insert>

        <insert tableName="mdm30_status_transition" dbms="postgresql, mssql, hsqldb">
            <column name="ID" value="1B69bec6-9960-11ec-b909-0242ac120002"/>
            <column name="START_STATUS" value="100da87c-8f05-11ec-b909-0242ac120002"/>
            <column name="END_STATUS" value="900da87c-8f05-11ec-b909-0242ac120002"/>
            <column name="STATUS_MODEL_ID" value="84e9750a-92e6-11ec-b909-0242ac120002"/>
            <column name="DESCRIPTION" value="Корректировка Документа"/>
            <column name="START_DATE" value="2015-01-01"/>
            <column name="END_DATE" value="9999-12-31"/>
            <column name="CREATED_BY" value="suvv-admin"/>
            <column name="CREATED_DATE" valueDate="${now}"/>
            <column name="LAST_MODIFIED_DATE" valueDate="${now}"/>
            <column name="version" value="1"/>
        </insert>

        <insert tableName="mdm30_status_transition" dbms="postgresql, mssql, hsqldb">
            <column name="ID" value="1C69bec6-9960-11ec-b909-0242ac120002"/>
            <column name="START_STATUS" value="1f90a87c-8f05-11ec-b909-0242ac120002"/>
            <column name="END_STATUS" value="600da87c-8f05-11ec-b909-0242ac120002"/>
            <column name="STATUS_MODEL_ID" value="84e9750a-92e6-11ec-b909-0242ac120002"/>
            <column name="DESCRIPTION" value="Закрытие задачи"/>
            <column name="START_DATE" value="2015-01-01"/>
            <column name="END_DATE" value="9999-12-31"/>
            <column name="CREATED_BY" value="suvv-admin"/>
            <column name="CREATED_DATE" valueDate="${now}"/>
            <column name="LAST_MODIFIED_DATE" valueDate="${now}"/>
            <column name="version" value="1"/>
        </insert>

        <insert tableName="mdm30_status_transition" dbms="postgresql, mssql, hsqldb">
            <column name="ID" value="1D69bec6-9960-11ec-b909-0242ac120002"/>
            <column name="START_STATUS" value="900da87c-8f05-11ec-b909-0242ac120002"/>
            <column name="END_STATUS" value="a00da87c-8f05-11ec-b909-0242ac120002"/>
            <column name="STATUS_MODEL_ID" value="84e9750a-92e6-11ec-b909-0242ac120002"/>
            <column name="DESCRIPTION" value=""/>
            <column name="START_DATE" value="2015-01-01"/>
            <column name="END_DATE" value="9999-12-31"/>
            <column name="CREATED_BY" value="suvv-admin"/>
            <column name="CREATED_DATE" valueDate="${now}"/>
            <column name="LAST_MODIFIED_DATE" valueDate="${now}"/>
            <column name="version" value="1"/>
        </insert>

        <insert tableName="mdm30_status_transition" dbms="postgresql, mssql, hsqldb">
        <column name="ID" value="1E69bec6-9960-11ec-b909-0242ac120002"/>
        <column name="START_STATUS" value="600da87c-8f05-11ec-b909-0242ac120002"/>
        <column name="STATUS_MODEL_ID" value="84e9750a-92e6-11ec-b909-0242ac120002"/>
        <column name="DESCRIPTION" value=""/>
        <column name="START_DATE" value="2015-01-01"/>
        <column name="END_DATE" value="9999-12-31"/>
        <column name="CREATED_BY" value="suvv-admin"/>
        <column name="CREATED_DATE" valueDate="${now}"/>
        <column name="LAST_MODIFIED_DATE" valueDate="${now}"/>
        <column name="version" value="1"/>
        </insert>



    </changeSet>

</databaseChangeLog>